pysqldf/__init__.py
pysqldf/load.py
pysqldf/sqldf.py
pysqldf/data/births_by_month.csv
pysqldf/data/iris.csv
pysqldf/data/meat.csv
pysqldf-1.2.3.dist-info/DESCRIPTION.rst
pysqldf-1.2.3.dist-info/METADATA
pysqldf-1.2.3.dist-info/RECORD
pysqldf-1.2.3.dist-info/WHEEL
pysqldf-1.2.3.dist-info/metadata.json
pysqldf-1.2.3.dist-info/top_level.txt
