Metadata-Version: 2.0
Name: pysqldf
Version: 1.2.3
Summary: sqldf for pandas
Home-page: https://github.com/airtoxin/pysqldf
Author: Ryoji Ishii
Author-email: airtoxin@icloud.com
License: MIT
Keywords: sqldf pandas dataframe sql pandasql
Platform: UNKNOWN
Classifier: Development Status :: 4 - Beta
Classifier: Intended Audience :: Developers
Classifier: License :: OSI Approved :: MIT License
Classifier: Programming Language :: Python :: 2.6
Classifier: Programming Language :: Python :: 2.7
Classifier: Programming Language :: Python :: 3.2
Classifier: Programming Language :: Python :: 3.3
Classifier: Programming Language :: Python :: 3.4
Classifier: Programming Language :: SQL
Classifier: Topic :: Software Development :: Libraries :: Python Modules
Classifier: Topic :: Utilities
Requires-Dist: pandas
